sentiment_lexicon/__init__.py
sentiment_lexicon/lexicon.py
sentiment_lexicon-0.2.3.dist-info/LICENSE
sentiment_lexicon-0.2.3.dist-info/METADATA
sentiment_lexicon-0.2.3.dist-info/WHEEL
sentiment_lexicon-0.2.3.dist-info/top_level.txt
sentiment_lexicon-0.2.3.dist-info/RECORD
