Metadata-Version: 2.1
Name: sentiment-lexicon
Version: 0.2.3
Summary: UNKNOWN
Home-page: https://github.com/emilbaekdahl/sentiment_lexicon
Author: Emil Bækdahl
Author-email: emilsbaekdahl@gmail.com
License: UNKNOWN
Project-URL: Source Code, https://github.com/emilbaekdahl/sentiment_lexicon
Project-URL: Documentation, https://emilbaekdahl.github.io/sentiment_lexicon/
Platform: UNKNOWN
Classifier: Development Status :: 4 - Beta
Classifier: Intended Audience :: Developers
Classifier: License :: OSI Approved :: MIT License
